{
 "absolute_value": 0,
 "align_labels_right": 0,
 "creation": "2025-05-23 21:46:33.091224",
 "css": ".uppercase {\n  text-transform: uppercase;\n}\n\n.form-container {\n    border: 1px solid black;\n    padding: 10px;\n}\n\n.print-format td, .print-format th {\n    vertical-align: top !important;\n    padding: 2px !important;\n}\n\n.print-format .table-bordered td, .print-format .table-bordered th {\n    border: 1px solid #000;\n}\n",
 "custom_format": 1,
 "default_print_language": "en",
 "disabled": 0,
 "doc_type": "Purchase Receipt",
 "docstatus": 0,
 "doctype": "Print Format",
 "font_size": 14,
 "html": "cek ssh",
 "idx": 0,
 "line_breaks": 0,
 "margin_bottom": 15.0,
 "margin_left": 15.0,
 "margin_right": 15.0,
 "margin_top": 15.0,
 "modified": "2025-05-24 09:00:12.783501",
 "modified_by": "Administrator",
 "module": "Intan Pariwara",
 "name": "Purchase Receipt",
 "owner": "Administrator",
 "page_number": "Hide",
 "print_format_builder": 0,
 "print_format_builder_beta": 0,
 "print_format_type": "Jinja",
 "raw_printing": 0,
 "show_section_headings": 0,
 "standard": "Yes"
}